hi2020/__init__.py
hi2020/calculate.py
hi2020/say.py
hi2020/bin/__init__.py
hi2020/bin/cli.py
hi2020/static/hi.js
hi2020-1.0.4.dist-info/LICENSE
hi2020-1.0.4.dist-info/METADATA
hi2020-1.0.4.dist-info/WHEEL
hi2020-1.0.4.dist-info/entry_points.txt
hi2020-1.0.4.dist-info/top_level.txt
hi2020-1.0.4.dist-info/RECORD
