Metadata-Version: 2.1
Name: hi2020
Version: 1.0.4
Summary: 一个hi问候包
Home-page: UNKNOWN
Author: happylay
License: Apache Software License
Keywords: hi2020 cli
Platform: UNKNOWN
Classifier: Programming Language :: Python :: 3
Classifier: License :: OSI Approved :: Apache Software License
Classifier: Operating System :: OS Independent
Requires-Python: >=3
Requires-Dist: click
